Metadata-Version: 2.1
Name: online_shop
Version: 0.1.0
Requires-Python: >=3.11
Requires-Dist: Django ==4.2.7
Requires-Dist: daphne ==4.0.0
Requires-Dist: psycopg2 ==2.9.9
Requires-Dist: djangorestframework
Requires-Dist: djangorestframework-simplejwt ==5.3.1
Requires-Dist: pillow ==10.1.0
Requires-Dist: django-extensions ==3.2.3
Requires-Dist: channels ==4.0.0
